scrapy_random_useragent_pro/__init__.py
scrapy_random_useragent_pro/middleware.py
scrapy_random_useragent_pro-1.0.0.dist-info/LICENSE
scrapy_random_useragent_pro-1.0.0.dist-info/METADATA
scrapy_random_useragent_pro-1.0.0.dist-info/WHEEL
scrapy_random_useragent_pro-1.0.0.dist-info/top_level.txt
scrapy_random_useragent_pro-1.0.0.dist-info/RECORD
